{
"type": "FeatureCollection",
"crs": { "type": "name", "properties": { "name": "urn:ogc:def:crs:OGC:1.3:CRS84" } },
                                                                                
"features": [
{ "type": "Feature", "properties": { "OBJECTID": 30, "NEIGHBOR": null, "FULLNAME": "Information", "SPACE": "ATDO.2051", "TYPE": "Information", "ART_ID": null, "TERMINAL": "AE", "GlobalID": "c6cd411a-dbac-4784-a8fb-ea0bebfb5876" }, "geometry": { "type": "Point", "coordinates": [ -75.246641860959215, 39.875301289783913 ] } },
{ "type": "Feature", "properties": { "OBJECTID": 31, "NEIGHBOR": null, "FULLNAME": "Information", "SPACE": "WTDO.2069", "TYPE": "Information", "ART_ID": null, "TERMINAL": "AW", "GlobalID": "ead7f6ea-f983-44a0-bbb7-eedf4374f1dc" }, "geometry": { "type": "Point", "coordinates": [ -75.250859302088358, 39.874617888129968 ] } },
{ "type": "Feature", "properties": { "OBJECTID": 32, "NEIGHBOR": null, "FULLNAME": "Information", "SPACE": "BTDO.2009", "TYPE": "Information", "ART_ID": null, "TERMINAL": "B", "GlobalID": "d7f0b2b9-b7ac-4525-9c47-169c9753c487" }, "geometry": { "type": "Point", "coordinates": [ -75.243758504263596, 39.875841079927568 ] } },
{ "type": "Feature", "properties": { "OBJECTID": 33, "NEIGHBOR": null, "FULLNAME": "Information", "SPACE": "CTDO.2059", "TYPE": "Information", "ART_ID": null, "TERMINAL": "C", "GlobalID": "d6bb256b-be1b-4eb1-96aa-fdf37f883e2d" }, "geometry": { "type": "Point", "coordinates": [ -75.24202330028649, 39.876185617245355 ] } },
{ "type": "Feature", "properties": { "OBJECTID": 34, "NEIGHBOR": null, "FULLNAME": "Information", "SPACE": "ETDO.2022", "TYPE": "Information", "ART_ID": null, "TERMINAL": "E", "GlobalID": "61365225-2eda-44c4-9ebf-5732cdd55bb8" }, "geometry": { "type": "Point", "coordinates": [ -75.239555408411363, 39.878554454600291 ] } },
{ "type": "Feature", "properties": { "OBJECTID": 35, "NEIGHBOR": null, "FULLNAME": "US Airways service counter", "SPACE": "WTAO.2080", "TYPE": "Information", "ART_ID": null, "TERMINAL": "AW", "GlobalID": "bfa8520e-a7f7-45ff-b866-1bf64964cce7" }, "geometry": { "type": "Point", "coordinates": [ -75.251074801776085, 39.874379317647559 ] } },
{ "type": "Feature", "properties": { "OBJECTID": 36, "NEIGHBOR": null, "FULLNAME": "Information", "SPACE": null, "TYPE": "Information", "ART_ID": null, "TERMINAL": "F", "GlobalID": "a607840e-0d95-4207-bed2-bbc426792519" }, "geometry": { "type": "Point", "coordinates": [ -75.237433366424995, 39.880573158796125 ] } },
{ "type": "Feature", "properties": { "OBJECTID": 38, "NEIGHBOR": null, "FULLNAME": "United Airlines Customer Service Kiosks", "SPACE": null, "TYPE": "Information", "ART_ID": null, "TERMINAL": "D", "GlobalID": "067e1af6-42a9-48ab-8cad-88126ab9dc96" }, "geometry": { "type": "Point", "coordinates": [ -75.237948063949446, 39.875372954908237 ] } },
{ "type": "Feature", "properties": { "OBJECTID": 89, "NEIGHBOR": "Security D\/E", "FULLNAME": "Information", "SPACE": null, "TYPE": "Information", "ART_ID": null, "TERMINAL": "D", "GlobalID": "013e3fb3-1caa-40ea-9453-479ddb92609b" }, "geometry": { "type": "Point", "coordinates": [ -75.239590462586193, 39.87769871624711 ] } },
{ "type": "Feature", "properties": { "OBJECTID": 90, "NEIGHBOR": null, "FULLNAME": "US Airways service counter", "SPACE": null, "TYPE": "Information", "ART_ID": null, "TERMINAL": "B", "GlobalID": "dfcd411a-5f65-4920-ab98-c5d78fe0441a" }, "geometry": { "type": "Point", "coordinates": [ -75.244207480030042, 39.873955320628944 ] } }
]
}
